secimport/__init__.py
secimport/backends/bpftrace_backend/__init__.py
secimport/backends/bpftrace_backend/actions/kill_on_processing.bt
secimport/backends/bpftrace_backend/actions/kill_process.bt
secimport/backends/bpftrace_backend/actions/log_file_system.bt
secimport/backends/bpftrace_backend/actions/log_network.bt
secimport/backends/bpftrace_backend/actions/log_python_module_entry.bt
secimport/backends/bpftrace_backend/actions/log_python_module_exit.bt
secimport/backends/bpftrace_backend/actions/log_syscall.bt
secimport/backends/bpftrace_backend/bpftrace_backend.py
secimport/backends/bpftrace_backend/default.template.bt
secimport/backends/bpftrace_backend/default.yaml.template.bt
secimport/backends/bpftrace_backend/filters/file_system.bt
secimport/backends/bpftrace_backend/filters/is_current_module_under_supervision.bt
secimport/backends/bpftrace_backend/filters/networking.bt
secimport/backends/bpftrace_backend/filters/processes.bt
secimport/backends/bpftrace_backend/generate_profile.bt
secimport/backends/bpftrace_backend/new_template.bt
secimport/backends/bpftrace_backend/probes/module_syscalls_allowlist_template.bt
secimport/backends/common/__init__.py
secimport/backends/common/instrumentation_backend.py
secimport/backends/common/system_calls.py
secimport/backends/common/utils.py
secimport/backends/dtrace_backend/__init__.py
secimport/backends/dtrace_backend/actions/kill_on_processing.d
secimport/backends/dtrace_backend/actions/kill_process.d
secimport/backends/dtrace_backend/actions/log_file_system.d
secimport/backends/dtrace_backend/actions/log_network.d
secimport/backends/dtrace_backend/actions/log_python_module_entry.d
secimport/backends/dtrace_backend/actions/log_python_module_exit.d
secimport/backends/dtrace_backend/actions/log_syscall.d
secimport/backends/dtrace_backend/default.allowlist.template.d
secimport/backends/dtrace_backend/default.blocklist.template.d
secimport/backends/dtrace_backend/default.template.d
secimport-0.11.0.dist-info/LICENSE
secimport-0.11.0.dist-info/METADATA
secimport-0.11.0.dist-info/WHEEL
secimport-0.11.0.dist-info/entry_points.txt
secimport-0.11.0.dist-info/RECORD
