Metadata-Version: 2.3
Name: secimport
Version: 0.11.0
Summary: A eBPF runtime sandbox for python that prevents RCE.
License: MIT
Author: Avi Lumelsky
Requires-Python: >=3.8,<4.0
Classifier: License :: OSI Approved :: MIT License
Classifier: Programming Language :: Python :: 3
Classifier: Programming Language :: Python :: 3.8
Classifier: Programming Language :: Python :: 3.9
Classifier: Programming Language :: Python :: 3.10
Classifier: Programming Language :: Python :: 3.11
Classifier: Programming Language :: Python :: 3.12
Classifier: Programming Language :: Python :: 3.13
Requires-Dist: PyYAML (>=6.0,<7.0)
Requires-Dist: typer (>=0.15.1,<0.16.0)
Project-URL: Homepage, https://github.com/avilum/secimport
